doseper/__init__.py
doseper/main.py
doseper-1.0.1.dist-info/LICENSE
doseper-1.0.1.dist-info/METADATA
doseper-1.0.1.dist-info/WHEEL
doseper-1.0.1.dist-info/entry_points.txt
doseper-1.0.1.dist-info/top_level.txt
doseper-1.0.1.dist-info/RECORD
