Metadata-Version: 2.2
Name: doseper
Version: 1.0.1
Summary: A tool for sending multiple HTTP requests for website testing
Home-page: https://github.com/HeronSky/doseper
Author: HeronSky
Author-email: heronskytw@gmail.com
Project-URL: Bug Tracker, https://github.com/HeronSky/doseper/issues
Classifier: Programming Language :: Python :: 3
Classifier: Operating System :: OS Independent
Requires-Python: >=3.6
License-File: LICENSE
Requires-Dist: requests
Dynamic: author
Dynamic: author-email
Dynamic: classifier
Dynamic: description
Dynamic: description-content-type
Dynamic: home-page
Dynamic: project-url
Dynamic: requires-dist
Dynamic: requires-python
Dynamic: summary
